mypcmonitor/__init__.py
mypcmonitor/core/__init__.py
mypcmonitor/core/cpu.py
mypcmonitor/core/memory.py
mypcmonitor/core/network.py
mypcmonitor/core/storage.py
mypcmonitor/local/__init__.py
mypcmonitor/local/cpu.py
mypcmonitor/local/main.py
mypcmonitor/local/main.tcss
mypcmonitor/local/memory.py
mypcmonitor/local/storage.py
mypcmonitor/models/__init__.py
mypcmonitor/models/metrics.py
mypcmonitor/utils.py
mypcmonitor-0.1.1.dist-info/METADATA
mypcmonitor-0.1.1.dist-info/WHEEL
mypcmonitor-0.1.1.dist-info/entry_points.txt
mypcmonitor-0.1.1.dist-info/RECORD
