Metadata-Version: 2.1
Name: mypcmonitor
Version: 0.1.1
Summary: 
Author: bdizen
Author-email: bdizenweb@gmail.com
Requires-Python: >=3.10,<4.0
Classifier: Programming Language :: Python :: 3
Classifier: Programming Language :: Python :: 3.10
Classifier: Programming Language :: Python :: 3.11
Classifier: Programming Language :: Python :: 3.12
Requires-Dist: psutil (>=7.0.0,<8.0.0)
Requires-Dist: textual (>=2.1.1,<3.0.0)
